easyfs/__init__.py
easyfs/directory.py
easyfs/file.py
easyfs-0.0.3.dist-info/METADATA
easyfs-0.0.3.dist-info/WHEEL
easyfs-0.0.3.dist-info/top_level.txt
easyfs-0.0.3.dist-info/RECORD
