Metadata-Version: 2.1
Name: easyfs
Version: 0.0.3
Requires-Dist: pydantic
Requires-Dist: fsspec
Requires-Dist: flatdict
Provides-Extra: cookiecutter
Requires-Dist: cookiecutter ; extra == 'cookiecutter'
